{
  "generatedAt": "2026-07-11T17:35:55.375Z",
  "topClientChunks": [
    {
      "name": "_nuxt/DUDug9Ca.js",
      "sizeKb": 460.64,
      "gzipKb": 158.74
    },
    {
      "name": "_nuxt/rD1edPUc.js",
      "sizeKb": 297.96,
      "gzipKb": 92.31
    },
    {
      "name": "_nuxt/Cn90WH12.js",
      "sizeKb": 275.64,
      "gzipKb": 85.44
    },
    {
      "name": "_nuxt/BC5N40np.js",
      "sizeKb": 144.85,
      "gzipKb": 26.2
    },
    {
      "name": "_nuxt/DTIbtCUb.js",
      "sizeKb": 80.79,
      "gzipKb": 27.9
    },
    {
      "name": "_nuxt/D6_sMQcq.js",
      "sizeKb": 53.29,
      "gzipKb": 14.62
    },
    {
      "name": "_nuxt/3P3VHtK8.js",
      "sizeKb": 44.39,
      "gzipKb": 14.03
    },
    {
      "name": "_nuxt/CKTHXMrv.js",
      "sizeKb": 41.48,
      "gzipKb": 11.99
    },
    {
      "name": "_nuxt/Dw0rLCLl.js",
      "sizeKb": 40.75,
      "gzipKb": 10.27
    },
    {
      "name": "_nuxt/RF3KqwAr.js",
      "sizeKb": 40.25,
      "gzipKb": 11.31
    }
  ],
  "totalOutputSize": {
    "total": "10.2 MB",
    "gzip": "2.71 MB gzip"
  }
}